pica/__init__.py
pica/connection.py
pica/cursor.py
pica/exceptions.py
pica/lazy_loader.py
pica_dbapi-0.1.3.dist-info/LICENSE
pica_dbapi-0.1.3.dist-info/METADATA
pica_dbapi-0.1.3.dist-info/WHEEL
pica_dbapi-0.1.3.dist-info/top_level.txt
pica_dbapi-0.1.3.dist-info/RECORD
