Metadata-Version: 2.2
Name: pica-dbapi
Version: 0.1.3
Summary: A lightweight and fun DBAPI built on pandas/csv 🎉. Supported SQL: SELECT, INSERT, UPDATE, DELETE, JOIN, GROUP BY.
Author-email: Naruhide KITADA <kitfactory@gmail.com>
License: MIT License
Project-URL: Homepage, https://github.com/kitfactory/pica
Project-URL: Documentation, https://github.com/kitfactory/pica#readme
Project-URL: Repository, https://github.com/kitfactory/pica
Classifier: Programming Language :: Python :: 3
Classifier: License :: OSI Approved :: MIT License
Classifier: Operating System :: OS Independent
Requires-Python: >=3.10
License-File: LICENSE
Requires-Dist: pandas>=1.0.0
Requires-Dist: sqlparse>=0.4.0
Requires-Dist: numpy>=1.18.0
